osiris_agent/__init__.py
osiris_agent/agent_node.py
osiris_agent-0.1.2.dist-info/licenses/LICENSE
osiris_agent-0.1.2.dist-info/METADATA
osiris_agent-0.1.2.dist-info/WHEEL
osiris_agent-0.1.2.dist-info/entry_points.txt
osiris_agent-0.1.2.dist-info/top_level.txt
osiris_agent-0.1.2.dist-info/RECORD
