Metadata-Version: 2.4
Name: osiris_agent
Version: 0.1.2
Summary: OSIRIS agent for ROS2/Humble
Home-page: https://github.com/nicolaselielll/osiris_agent
Author: Nicolas Tuomaala
Author-email: nicolas.tuomaala00@gmail.com
License: Apache-2.0
Keywords: ros2 humble agent
Classifier: Development Status :: 4 - Beta
Classifier: Intended Audience :: Developers
Classifier: License :: OSI Approved :: Apache Software License
Classifier: Programming Language :: Python :: 3
Classifier: Programming Language :: Python :: 3 :: Only
Classifier: Operating System :: OS Independent
License-File: LICENSE
Requires-Dist: websockets
Requires-Dist: psutil
Provides-Extra: ros
Requires-Dist: rclpy; extra == "ros"
Dynamic: author
Dynamic: author-email
Dynamic: classifier
Dynamic: description
Dynamic: description-content-type
Dynamic: home-page
Dynamic: keywords
Dynamic: license
Dynamic: license-file
Dynamic: provides-extra
Dynamic: requires-dist
Dynamic: summary
